LICENSE
MANIFEST.in
README.md
setup.py
examples/__init__.py
examples/train.py
examples/core/__init__.py
examples/core/builder.py
examples/core/models/__init__.py
examples/core/models/mzi_cnn.py
torchonn/__init__.py
torchonn/version.py
torchonn.egg-info/PKG-INFO
torchonn.egg-info/SOURCES.txt
torchonn.egg-info/dependency_links.txt
torchonn.egg-info/requires.txt
torchonn.egg-info/top_level.txt
torchonn/devices/__init__.py
torchonn/devices/mrr.py
torchonn/layers/__init__.py
torchonn/layers/activation.py
torchonn/layers/base_layer.py
torchonn/layers/fftonn_conv2d.py
torchonn/layers/fftonn_linear.py
torchonn/layers/morr_conv2d.py
torchonn/layers/morr_linear.py
torchonn/layers/mrr_conv2d.py
torchonn/layers/mrr_linear.py
torchonn/layers/mzi_conv2d.py
torchonn/layers/mzi_linear.py
torchonn/layers/pcm_conv2d.py
torchonn/layers/pcm_linear.py
torchonn/layers/super_conv2d.py
torchonn/layers/super_linear.py
torchonn/layers/super_mesh.py
torchonn/layers/utils.py
torchonn/models/__init__.py
torchonn/models/base_model.py
torchonn/op/__init__.py
torchonn/op/butterfly_op.py
torchonn/op/cross_op.py
torchonn/op/dc_op.py
torchonn/op/matrix_parametrization.py
torchonn/op/mmi_op.py
torchonn/op/mrr_op.py
torchonn/op/mzi_op.py
torchonn/op/nonlinear_op.py
torchonn/op/pcm_op.py
torchonn/op/cuda_extension/hadamard_cuda/hadamard_cuda.cpp
torchonn/op/cuda_extension/hadamard_cuda/hadamard_cuda_kernel.cu
torchonn/op/cuda_extension/matrix_parametrization/matrix_parametrization_cuda.cpp
torchonn/op/cuda_extension/matrix_parametrization/matrix_parametrization_cuda_kernel.cu
torchonn/op/cuda_extension/universal_cuda/universal_cuda.cpp
torchonn/op/cuda_extension/universal_cuda/universal_cuda_kernel.cu
unitest/__init__.py
unitest/test_build_weight.py
unitest/test_layers.py
unitest/test_models.py
unitest/test_op.py