Metadata-Version: 2.1
Name: torchonn
Version: 0.0.8
Summary: Pytorch-centric Optical Neural Network Library
Home-page: https://github.com/JeremieMelo/pytorch-onn
Author: Jiaqi Gu
Author-email: jqgu@utexas.edu
License: MIT
Classifier: Development Status :: 3 - Alpha
Classifier: Intended Audience :: Education
Classifier: Intended Audience :: Science/Research
Classifier: License :: OSI Approved :: Apache Software License
Classifier: Programming Language :: Python :: 3.6
Classifier: Programming Language :: Python :: 3.7
Classifier: Programming Language :: Python :: 3.8
Classifier: Topic :: Scientific/Engineering
Classifier: Topic :: Scientific/Engineering :: Artificial Intelligence
Classifier: Topic :: Software Development
Classifier: Topic :: Software Development :: Libraries
Classifier: Topic :: Software Development :: Libraries :: Python Modules
Requires-Python: >=3.6
License-File: LICENSE
Requires-Dist: numpy>=1.19.2
Requires-Dist: torchvision>=0.9.0.dev20210130
Requires-Dist: tqdm>=4.56.0
Requires-Dist: setuptools>=52.0.0
Requires-Dist: torch>=1.13.0
Requires-Dist: pyutils>=0.0.1
Requires-Dist: matplotlib>=3.3.4
Requires-Dist: svglib>=1.1.0
Requires-Dist: scipy>=1.5.4
Requires-Dist: scikit-learn>=0.24.1
Requires-Dist: torchsummary>=1.5.1
Requires-Dist: pyyaml>=5.1.1
Requires-Dist: tensorflow>=2.5.0
